.travis.yml
AUTHORS
ChangeLog
LICENSE
README.md
setup.cfg
setup.py
tox.ini
pytest_blink1/__init__.py
pytest_blink1.egg-info/PKG-INFO
pytest_blink1.egg-info/SOURCES.txt
pytest_blink1.egg-info/dependency_links.txt
pytest_blink1.egg-info/entry_points.txt
pytest_blink1.egg-info/not-zip-safe
pytest_blink1.egg-info/pbr.json
pytest_blink1.egg-info/top_level.txt
tests/conftest.py
tests/test_blink1.py