Metadata-Version: 1.1
Name: pytest-blink1
Version: 0.0.8
Summary: Pytest plugin to emit notifications via the Blink(1) RGB LED
Home-page: https://github.com/vmalloc/pytest-blink1
Author: Rotem Yaari
Author-email: vmalloc@gmail.com
License: MIT
Platform: UNKNOWN
Classifier: Development Status :: 4 - Beta
Classifier: Intended Audience :: Developers
Classifier: Operating System :: OS Independent
Classifier: Programming Language :: Python
Classifier: License :: OSI Approved :: MIT License
